apple_metal/__init__.py
apple_metal/add.py
apple_metal-0.0.1.dist-info/METADATA
apple_metal-0.0.1.dist-info/WHEEL
apple_metal-0.0.1.dist-info/licenses/LICENSE
apple_metal-0.0.1.dist-info/RECORD
