Metadata-Version: 2.3
Name: apple_metal
Version: 0.0.1
Summary: A python package to interact with apple's Metal API
Author-email: Alois Denoiseux <aloisdenoiseux@gmail.com>
License-File: LICENSE
Classifier: License :: OSI Approved :: MIT License
Classifier: Operating System :: MacOS :: MacOS X
Classifier: Programming Language :: Python :: 3
Requires-Python: >=3.1
